apeye/__init__.py
apeye/cache.py
apeye/email_validator.py
apeye/public_suffix_list.dat
apeye/py.typed
apeye/rate_limiter.py
apeye/requests_url.py
apeye/url.py
apeye/slumber_url/__init__.py
apeye/slumber_url/exceptions.py
apeye/slumber_url/serializers/__init__.py
apeye/slumber_url/serializers/_abc.py
apeye/slumber_url/serializers/_pyyaml_serializer.py
apeye/slumber_url/serializers/_ruamel_serializer.py
apeye-1.3.0.dist-info/LICENSE
apeye-1.3.0.dist-info/WHEEL
apeye-1.3.0.dist-info/METADATA
apeye-1.3.0.dist-info/RECORD
