Metadata-Version: 2.1
Name: apeye
Version: 1.3.0
Summary: Handy tools for working with URLs and APIs.
Keywords: api,cache,requests,rest,url
Author-email: Dominic Davis-Foster <dominic@davis-foster.co.uk>
Requires-Python: >=3.6.1
Classifier: Development Status :: 5 - Production/Stable
Classifier: Intended Audience :: Developers
Classifier: License :: OSI Approved :: GNU Lesser General Public License v3 or later (LGPLv3+)
Classifier: Operating System :: OS Independent
Classifier: Programming Language :: Python
Classifier: Programming Language :: Python :: 3 :: Only
Classifier: Programming Language :: Python :: 3.6
Classifier: Programming Language :: Python :: 3.7
Classifier: Programming Language :: Python :: 3.8
Classifier: Programming Language :: Python :: 3.9
Classifier: Programming Language :: Python :: 3.10
Classifier: Programming Language :: Python :: 3.11
Classifier: Programming Language :: Python :: Implementation :: CPython
Classifier: Programming Language :: Python :: Implementation :: PyPy
Classifier: Topic :: Internet :: WWW/HTTP
Classifier: Topic :: Software Development :: Libraries :: Python Modules
Classifier: Typing :: Typed
Requires-Dist: apeye-core>=1.0.0b2
Requires-Dist: domdf-python-tools>=2.6.0
Requires-Dist: platformdirs>=2.3.0
Requires-Dist: requests>=2.24.0
Requires-Dist: cachecontrol[filecache]>=0.12.6 ; extra == "all"
Requires-Dist: lockfile>=0.12.2 ; extra == "all"
Requires-Dist: cachecontrol[filecache]>=0.12.6 ; extra == "limiter"
Requires-Dist: lockfile>=0.12.2 ; extra == "limiter"
Project-URL: Documentation, https://apeye.readthedocs.io/en/latest
Project-URL: Homepage, https://github.com/domdfcoding/apeye
Project-URL: Issue Tracker, https://github.com/domdfcoding/apeye/issues
Project-URL: Source Code, https://github.com/domdfcoding/apeye
Provides-Extra: all
Provides-Extra: limiter
